{
	"parameters": {
		"console.controller_name_converter.class": "pymfony.bundle.framework_bundle.console.ControllerNameParser",
		"console_kernel.class": "pymfony.bundle.framework_bundle.console.ConsoleKernel",
		"console.command_resolver.class": "pymfony.bundle.framework_bundle.controller.ControllerResolver",
		"console.response_listener.class": "pymfony.component.console_kernel.listener.ResponseListener",
		"console.exception_listener.class": "pymfony.component.console_kernel.listener.ExceptionListener"
		},
	"services": {
		"console.controller_name_converter": {
			"class": "%console.controller_name_converter.class%",
			"arguments": [
				"@kernel"
			]
		},
		"console.command_resolver": {
			"class": "%console.command_resolver.class%",
			"arguments": [
				"@service_container",
				"@console.controller_name_converter"
			]
		},
		"console_kernel": {
			"class": "%console_kernel.class%",
			"arguments": [
				"@event_dispatcher",
				"@service_container",
				"@console.command_resolver"
			]
		},
		"console.response_listener": {
			"class": "%console.response_listener.class%",
			"tags": [
				{"name": "kernel.event_subscriber"}
			],
			"arguments": [
			]
		},
		"console.exception_listener": {
			"class": "%console.exception_listener.class%",
			"tags": [
				{"name": "kernel.event_subscriber"}
			],
			"arguments": [
				"%console.exception_controller%"
			]
		}
	}
}
